ghs_hazard_pictogram/__init__.py
ghs_hazard_pictogram/data.py
ghs_hazard_pictogram/tests.py
ghs_hazard_pictogram/pictograms/class3.svg
ghs_hazard_pictogram/pictograms/class62.svg
ghs_hazard_pictogram/pictograms/class7a.svg
ghs_hazard_pictogram/pictograms/class7b.svg
ghs_hazard_pictogram/pictograms/class7c.svg
ghs_hazard_pictogram/pictograms/class7e.svg
ghs_hazard_pictogram/pictograms/class8.svg
ghs_hazard_pictogram/pictograms/class9.svg
ghs_hazard_pictogram/pictograms/division11.svg
ghs_hazard_pictogram/pictograms/division12.svg
ghs_hazard_pictogram/pictograms/division13.svg
ghs_hazard_pictogram/pictograms/division14.svg
ghs_hazard_pictogram/pictograms/division15.svg
ghs_hazard_pictogram/pictograms/division16.svg
ghs_hazard_pictogram/pictograms/division21.svg
ghs_hazard_pictogram/pictograms/division22.svg
ghs_hazard_pictogram/pictograms/division23.svg
ghs_hazard_pictogram/pictograms/division41.svg
ghs_hazard_pictogram/pictograms/division42.svg
ghs_hazard_pictogram/pictograms/division43.svg
ghs_hazard_pictogram/pictograms/division51.svg
ghs_hazard_pictogram/pictograms/division52.svg
ghs_hazard_pictogram/pictograms/division61.svg
ghs_hazard_pictogram/pictograms/ghs01.svg
ghs_hazard_pictogram/pictograms/ghs02.svg
ghs_hazard_pictogram/pictograms/ghs03.svg
ghs_hazard_pictogram/pictograms/ghs04.svg
ghs_hazard_pictogram/pictograms/ghs05.svg
ghs_hazard_pictogram/pictograms/ghs06.svg
ghs_hazard_pictogram/pictograms/ghs07.svg
ghs_hazard_pictogram/pictograms/ghs08.svg
ghs_hazard_pictogram/pictograms/ghs09.svg
ghs_hazard_pictogram-0.1.0.dist-info/LICENSE
ghs_hazard_pictogram-0.1.0.dist-info/METADATA
ghs_hazard_pictogram-0.1.0.dist-info/WHEEL
ghs_hazard_pictogram-0.1.0.dist-info/top_level.txt
ghs_hazard_pictogram-0.1.0.dist-info/RECORD
