Metadata-Version: 2.1
Name: ghs-hazard-pictogram
Version: 0.1.0
Summary: GHS hazard descriptions and pictograms.
Home-page: https://github.com/fmeurou/ghs_hazard_pictograms
Author: Frédéric MEUROU
Author-email: fm@peabytes.me
License: UNKNOWN
Platform: UNKNOWN
Classifier: Intended Audience :: Information Technology
Classifier: Development Status :: 4 - Beta
Classifier: Operating System :: OS Independent
Classifier: Programming Language :: Python
Classifier: Programming Language :: Python :: 3
Classifier: Programming Language :: Python :: 3 :: Only
Classifier: Natural Language :: English
Classifier: License :: OSI Approved :: MIT License
Classifier: Topic :: Scientific/Engineering
Classifier: Topic :: Scientific/Engineering :: Chemistry
Requires-Python: >3.7.0
